packingslip/__init__.py
packingslip/packingslip.py
packingslip/spotcheck.py
packingslip-0.1.0.dist-info/DESCRIPTION.rst
packingslip-0.1.0.dist-info/METADATA
packingslip-0.1.0.dist-info/RECORD
packingslip-0.1.0.dist-info/WHEEL
packingslip-0.1.0.dist-info/entry_points.txt
packingslip-0.1.0.dist-info/metadata.json
packingslip-0.1.0.dist-info/top_level.txt
