Metadata-Version: 2.0
Name: packingslip
Version: 0.1.0
Summary: Tools to compare files by checksum.
Home-page: https://github.com/dmwilcox/packingslip
Author: Yuba Solutions LLC
Author-email: dmw@yubasoluions.com
License: GPL
Keywords: rsync
Platform: UNKNOWN
Classifier: Development Status :: 3 - Alpha
Classifier: Environment :: Console
Classifier: Intended Audience :: End Users/Desktop
Classifier: License :: OSI Approved :: GNU General Public License (GPL)
Classifier: Operating System :: POSIX
Classifier: Programming Language :: Python :: 2.7
Classifier: Programming Language :: Python :: 3
Classifier: Programming Language :: Python :: 3.4
Classifier: Topic :: Utilities
Requires-Dist: PyYAML
Requires-Dist: argparse
